digestparser/__init__.py
digestparser/build.py
digestparser/conf.py
digestparser/html.py
digestparser/jats.py
digestparser/json_output.py
digestparser/medium_post.py
digestparser/objects.py
digestparser/output.py
digestparser/parse.py
digestparser/utils.py
digestparser/zip.py
digestparser-0.2.0.dist-info/LICENSE
digestparser-0.2.0.dist-info/METADATA
digestparser-0.2.0.dist-info/WHEEL
digestparser-0.2.0.dist-info/top_level.txt
digestparser-0.2.0.dist-info/RECORD
