Metadata-Version: 2.1
Name: digestparser
Version: 0.2.0
Summary: Parse docx file containing article digest content
Home-page: https://github.com/elifesciences/digest-parser
Maintainer: eLife Sciences Publications Ltd.
Maintainer-email: tech-team@elifesciences.org
License: MIT
Classifier: Development Status :: 3 - Alpha
Classifier: Intended Audience :: Developers
Classifier: License :: OSI Approved :: MIT License
Classifier: Programming Language :: Python :: 3
License-File: LICENSE
Requires-Dist: python-docx
Requires-Dist: elifetools
